resumeanalyser/__init__.py
resumeanalyser/metrics.py
resumeanalyser/plotting.py
resumeanalyser/text_cleaning.py
resumeanalyser/text_reading.py
resumeanalyser-1.0.4.dist-info/LICENSE
resumeanalyser-1.0.4.dist-info/METADATA
resumeanalyser-1.0.4.dist-info/WHEEL
resumeanalyser-1.0.4.dist-info/RECORD
