Metadata-Version: 2.1
Name: resumeanalyser
Version: 1.0.4
Summary: The ResumeAnalyser package is a comprehensive toolkit designed for automated and efficient parsing, analysis, and evaluation of resumes.
License: MIT
Author: Xiangshen Yu
Requires-Python: >=3.11.6,<4.0.0
Classifier: License :: OSI Approved :: MIT License
Classifier: Programming Language :: Python :: 3
Classifier: Programming Language :: Python :: 3.12
Requires-Dist: matplotlib (>=3.8.2,<4.0.0)
Requires-Dist: nltk (>=3.8.1,<4.0.0)
Requires-Dist: pypdf (>=3.17.4,<4.0.0)
Requires-Dist: python-docx (>=1.1.0,<2.0.0)
Requires-Dist: scikit-learn (==1.4.0)
Requires-Dist: spacy (==3.7.2)
Requires-Dist: wordcloud (>=1.9.3,<2.0.0)
